aliyunsdkdds/__init__.py
aliyunsdkdds/endpoint.py
aliyunsdkdds/request/__init__.py
aliyunsdkdds/request/v20151201/AllocateDBInstanceSrvNetworkAddressRequest.py
aliyunsdkdds/request/v20151201/AllocateNodePrivateNetworkAddressRequest.py
aliyunsdkdds/request/v20151201/AllocatePublicNetworkAddressRequest.py
aliyunsdkdds/request/v20151201/CheckCloudResourceAuthorizedRequest.py
aliyunsdkdds/request/v20151201/CheckRecoveryConditionRequest.py
aliyunsdkdds/request/v20151201/CheckServiceLinkedRoleRequest.py
aliyunsdkdds/request/v20151201/CreateAccountRequest.py
aliyunsdkdds/request/v20151201/CreateBackupRequest.py
aliyunsdkdds/request/v20151201/CreateDBInstanceRequest.py
aliyunsdkdds/request/v20151201/CreateGlobalSecurityIPGroupRequest.py
aliyunsdkdds/request/v20151201/CreateNodeBatchRequest.py
aliyunsdkdds/request/v20151201/CreateNodeRequest.py
aliyunsdkdds/request/v20151201/CreateShardingDBInstanceRequest.py
aliyunsdkdds/request/v20151201/DeleteDBInstanceRequest.py
aliyunsdkdds/request/v20151201/DeleteGlobalSecurityIPGroupRequest.py
aliyunsdkdds/request/v20151201/DeleteNodeRequest.py
aliyunsdkdds/request/v20151201/DescribeAccountsRequest.py
aliyunsdkdds/request/v20151201/DescribeActiveOperationMaintenanceConfigRequest.py
aliyunsdkdds/request/v20151201/DescribeActiveOperationTaskCountRequest.py
aliyunsdkdds/request/v20151201/DescribeActiveOperationTaskRegionRequest.py
aliyunsdkdds/request/v20151201/DescribeActiveOperationTaskRequest.py
aliyunsdkdds/request/v20151201/DescribeActiveOperationTaskTypeRequest.py
aliyunsdkdds/request/v20151201/DescribeActiveOperationTasksRequest.py
aliyunsdkdds/request/v20151201/DescribeAuditLogFilterRequest.py
aliyunsdkdds/request/v20151201/DescribeAuditPolicyRequest.py
aliyunsdkdds/request/v20151201/DescribeAuditRecordsRequest.py
aliyunsdkdds/request/v20151201/DescribeAvailabilityZonesRequest.py
aliyunsdkdds/request/v20151201/DescribeAvailableEngineVersionRequest.py
aliyunsdkdds/request/v20151201/DescribeAvailableResourceRequest.py
aliyun_python_sdk_dds-3.7.24.dist-info/LICENSE
aliyun_python_sdk_dds-3.7.24.dist-info/METADATA
aliyun_python_sdk_dds-3.7.24.dist-info/WHEEL
aliyun_python_sdk_dds-3.7.24.dist-info/top_level.txt
aliyun_python_sdk_dds-3.7.24.dist-info/RECORD
